pyrede
