Metadata-Version: 2.1
Name: pyrede
Version: 0.0.3
Summary: A Redis dehydrator module.
Home-page: https://github.com/fanjindong/pyrede
Author: Jindong Fan
Author-email: 765912710@qq.com
License: MIT
Platform: UNKNOWN
Classifier: License :: OSI Approved :: MIT License
Classifier: Programming Language :: Python
Classifier: Programming Language :: Python :: 3
Classifier: Programming Language :: Python :: 3.6
Classifier: Programming Language :: Python :: Implementation :: CPython
Classifier: Programming Language :: Python :: Implementation :: PyPy
Requires-Python: >=3.6.0
